MANIFEST.in
README.txt
setup.py
moodle2edx/__init__.py
moodle2edx/abox.py
moodle2edx/main.py
moodle2edx.egg-info/PKG-INFO
moodle2edx.egg-info/SOURCES.txt
moodle2edx.egg-info/dependency_links.txt
moodle2edx.egg-info/entry_points.txt
moodle2edx.egg-info/requires.txt
moodle2edx.egg-info/top_level.txt
moodle2edx/test/__init__.py
moodle2edx/test/test_examples.py
moodle2edx/testdat/intro_to_stats.mbz