Metadata-Version: 1.0
Name: moodle2edx
Version: 0.1.0
Summary: Converter from latex to edX XML format course content files.
Home-page: http://pypi.python.org/pypi/moodle2edx/
Author: I. Chuang
Author-email: ichuang@mit.edu
License: LICENSE.txt
Platform: UNKNOWN
